{
  "themes": [
    {
      "id": 19,
      "name": "Alimentation",
      "codeName": "alimentation",
      "division": {
        "id": "1",
        "name": "Radio-Canada"
      },
      "lineupLink": {
        "href": "https://services.radio-canada.ca/neuro/v1/themes/19/lineup"
      }
    },
    {
      "id": 7,
      "name": "Art de vivre",
      "codeName": "plaisirs",
      "division": {
        "id": "1",
        "name": "Radio-Canada"
      },
      "lineupLink": {
        "href": "https://services.radio-canada.ca/neuro/v1/themes/7/lineup"
      }
    },
    {
      "id": 11,
      "name": "Arts",
      "codeName": "arts-et-divertissement",
      "division": {
        "id": "1",
        "name": "Radio-Canada"
      },
      "lineupLink": {
        "href": "https://services.radio-canada.ca/neuro/v1/themes/11/lineup"
      }
    },
    {
      "id": 16,
      "name": "Divertissement",
      "codeName": "dramatique-et-varietes",
      "division": {
        "id": "1",
        "name": "Radio-Canada"
      },
      "lineupLink": {
        "href": "https://services.radio-canada.ca/neuro/v1/themes/16/lineup"
      }
    },
    {
      "id": 5,
      "name": "Économie",
      "codeName": "economie",
      "division": {
        "id": "1",
        "name": "Radio-Canada"
      },
      "lineupLink": {
        "href": "https://services.radio-canada.ca/neuro/v1/themes/5/lineup"
      }
    },
    {
      "id": 15,
      "name": "Environnement",
      "codeName": "environnement",
      "division": {
        "id": "1",
        "name": "Radio-Canada"
      },
      "lineupLink": {
        "href": "https://services.radio-canada.ca/neuro/v1/themes/15/lineup"
      }
    },
    {
      "id": 22,
      "name": "Fiction",
      "codeName": "fiction",
      "division": {
        "id": "1",
        "name": "Radio-Canada"
      },
      "lineupLink": {
        "href": "https://services.radio-canada.ca/neuro/v1/themes/22/lineup"
      }
    },
    {
      "id": 1,
      "name": "Grands Titres",
      "codeName": "grands-titres",
      "division": {
        "id": "1",
        "name": "Radio-Canada"
      },
      "lineupLink": {
        "href": "https://services.radio-canada.ca/neuro/v1/themes/1/lineup"
      }
    },
    {
      "id": 20,
      "name": "Insolite",
      "codeName": "insolite",
      "division": {
        "id": "1",
        "name": "Radio-Canada"
      },
      "lineupLink": {
        "href": "https://services.radio-canada.ca/neuro/v1/themes/20/lineup"
      }
    },
    {
      "id": 2,
      "name": "International",
      "codeName": "international",
      "division": {
        "id": "1",
        "name": "Radio-Canada"
      },
      "lineupLink": {
        "href": "https://services.radio-canada.ca/neuro/v1/themes/2/lineup"
      }
    },
    {
      "id": 18,
      "name": "Justice et faits divers",
      "codeName": "faits-divers",
      "division": {
        "id": "1",
        "name": "Radio-Canada"
      },
      "lineupLink": {
        "href": "https://services.radio-canada.ca/neuro/v1/themes/18/lineup"
      }
    },
    {
      "id": 23,
      "name": "Music",
      "codeName": "music",
      "division": {
        "id": "2",
        "name": "CBC"
      },
      "lineupLink": {
        "href": "https://services.radio-canada.ca/neuro/v1/themes/23/lineup"
      }
    },
    {
      "id": 21,
      "name": "Musique",
      "codeName": "musique",
      "division": {
        "id": "1",
        "name": "Radio-Canada"
      },
      "lineupLink": {
        "href": "https://services.radio-canada.ca/neuro/v1/themes/21/lineup"
      }
    },
    {
      "id": 4,
      "name": "National",
      "codeName": "national",
      "division": {
        "id": "1",
        "name": "Radio-Canada"
      },
      "lineupLink": {
        "href": "https://services.radio-canada.ca/neuro/v1/themes/4/lineup"
      }
    },
    {
      "id": 13,
      "name": "Politique",
      "codeName": "politique",
      "division": {
        "id": "1",
        "name": "Radio-Canada"
      },
      "lineupLink": {
        "href": "https://services.radio-canada.ca/neuro/v1/themes/13/lineup"
      }
    },
    {
      "id": 12,
      "name": "Réflexion",
      "codeName": "reflexion",
      "division": {
        "id": "1",
        "name": "Radio-Canada"
      },
      "lineupLink": {
        "href": "https://services.radio-canada.ca/neuro/v1/themes/12/lineup"
      }
    },
    {
      "id": 3,
      "name": "Régional",
      "codeName": "regional",
      "division": {
        "id": "1",
        "name": "Radio-Canada"
      },
      "lineupLink": {
        "href": "https://services.radio-canada.ca/neuro/v1/themes/3/lineup"
      }
    },
    {
      "id": 8,
      "name": "Santé",
      "codeName": "sante",
      "division": {
        "id": "1",
        "name": "Radio-Canada"
      },
      "lineupLink": {
        "href": "https://services.radio-canada.ca/neuro/v1/themes/8/lineup"
      }
    },
    {
      "id": 10,
      "name": "Science",
      "codeName": "science",
      "division": {
        "id": "1",
        "name": "Radio-Canada"
      },
      "lineupLink": {
        "href": "https://services.radio-canada.ca/neuro/v1/themes/10/lineup"
      }
    },
    {
      "id": 17,
      "name": "Société",
      "codeName": "societe",
      "division": {
        "id": "1",
        "name": "Radio-Canada"
      },
      "lineupLink": {
        "href": "https://services.radio-canada.ca/neuro/v1/themes/17/lineup"
      }
    },
    {
      "id": 6,
      "name": "Sports",
      "codeName": "sports",
      "division": {
        "id": "1",
        "name": "Radio-Canada"
      },
      "lineupLink": {
        "href": "https://services.radio-canada.ca/neuro/v1/themes/6/lineup"
      }
    },
    {
      "id": 14,
      "name": "Syndicats et Affaires",
      "codeName": "syndicats-et-affaires",
      "division": {
        "id": "1",
        "name": "Radio-Canada"
      },
      "lineupLink": {
        "href": "https://services.radio-canada.ca/neuro/v1/themes/14/lineup"
      }
    },
    {
      "id": 9,
      "name": "Techno",
      "codeName": "technologie",
      "division": {
        "id": "1",
        "name": "Radio-Canada"
      },
      "lineupLink": {
        "href": "https://services.radio-canada.ca/neuro/v1/themes/9/lineup"
      }
    },
    {
      "id": 24,
      "name": "Version",
      "codeName": "version",
      "division": {
        "id": "1",
        "name": "Radio-Canada"
      },
      "lineupLink": {
        "href": "https://services.radio-canada.ca/neuro/v1/themes/24/lineup"
      }
    }
  ]
}
